{
  "4420100": {
    "proofs": {
      "risc0": [
        "Failed to validate block: Transaction { transaction_hash: Hash<32>(\"d8464433f4fd3ef4d502554da89876ad95a8e3503124c4d800d4fb0a14a53e0c\"), transaction_index: 0, violation: Inputs(UnknownInput(TransactionInput { transaction_id: Hash<32>(\"ffd203301e5416ecf3fb194a5d96bbfbca494800eeae4ae0ef0ad1eb8b45604c\"), index: 0 })) }\n\"\""
      ]
    }
  },
  "4420200": {
    "proofs": {
      "risc0": [
        "\"\""
      ]
    }
  },
  "4420400": {
    "proofs": {
      "risc0": [
        "\"\""
      ]
    }
  },
  "4420500": {
    "proofs": {
      "risc0": [
        "\"\""
      ]
    }
  },
  "4420600": {
    "proofs": {
      "risc0": [
        "\"\""
      ]
    }
  },
  "4420700": {
    "proofs": {
      "risc0": [
        "\"\""
      ]
    }
  },
  "4420800": {
    "proofs": {
      "risc0": [
        "\"\""
      ]
    }
  },
  "4420900": {
    "proofs": {
      "risc0": [
        "Failed to validate block: Transaction { transaction_hash: Hash<32>(\"b2041d71ad8110555c1109ec5bd1d4b5ecae563fc04b18ce51ee6c17dae4a663\"), transaction_index: 0, violation: Inputs(UnknownInput(TransactionInput { transaction_id: Hash<32>(\"2164285840de392aca85117e8b75eb4e90d4fe43d0cbf4a5ad6c4593ded5c2c9\"), index: 1 })) }\n\"\""
      ]
    }
  },
  "4421000": {
    "proofs": {
      "risc0": [
        "Failed to validate block: Transaction { transaction_hash: Hash<32>(\"cfd09f03ad341556294a48b14a9862ad97d3eb35a1968d81d9c3a8e91b662acb\"), transaction_index: 0, violation: Inputs(UnknownInput(TransactionInput { transaction_id: Hash<32>(\"cabcc3e9bc4c8166d0d89973823a7c55e06ea74940e43529767f09817e16951c\"), index: 0 })) }\n\"\""
      ]
    }
  },
  "4421200": {
    "proofs": {
      "risc0": [
        "\"\""
      ]
    }
  },
  "4421300": {
    "proofs": {
      "risc0": [
        "\"\""
      ]
    }
  },
  "4421400": {
    "proofs": {
      "risc0": [
        "\"\""
      ]
    }
  },
  "4421600": {
    "proofs": {
      "risc0": [
        "\"\""
      ]
    }
  },
  "4421700": {
    "proofs": {
      "risc0": [
        "Failed to validate block: Transaction { transaction_hash: Hash<32>(\"e538da0bab1756c66eda78864d2af6e63352818af0422dba51f5a3eda9bcab64\"), transaction_index: 0, violation: Inputs(UnknownInput(TransactionInput { transaction_id: Hash<32>(\"25afea2c2e1a1fe0794ac1ebb846ea8e4de39cf166d13ebde285421f065fd20f\"), index: 1 })) }\n\"\""
      ]
    }
  },
  "4421800": {
    "proofs": {
      "risc0": [
        "Failed to validate block: Transaction { transaction_hash: Hash<32>(\"c4eee827b767b203d070dd2c293b6b30b813f14b155b589ac23d2a353f970781\"), transaction_index: 0, violation: Inputs(UnknownInput(TransactionInput { transaction_id: Hash<32>(\"d8c270d48a0ed992213da002e93c27226f5010973d80c97d833bf608e711bdc9\"), index: 0 })) }\n\"\""
      ]
    }
  },
  "4422000": {
    "proofs": {
      "risc0": [
        "Failed to validate block: Transaction { transaction_hash: Hash<32>(\"f1dacb7ef52bf773562c68e373a0c1ca8e894412ffb7db19941e121c2c678ebe\"), transaction_index: 0, violation: Inputs(UnknownInput(TransactionInput { transaction_id: Hash<32>(\"ffd203301e5416ecf3fb194a5d96bbfbca494800eeae4ae0ef0ad1eb8b45604c\"), index: 0 })) }\n\"\""
      ]
    }
  },
  "4422100": {
    "proofs": {
      "risc0": [
        "\"\""
      ]
    }
  },
  "4422300": {
    "proofs": {
      "risc0": [
        "Failed to validate block: Transaction { transaction_hash: Hash<32>(\"105ac1788c62ae803dcbf9cee14920aa24a6eb547d45c8678936a21739ab29ef\"), transaction_index: 0, violation: Inputs(UnknownInput(TransactionInput { transaction_id: Hash<32>(\"4b61acedca6426ec989ef78a85ed97a8b4ffd47d9c40d4155e453d7e6b25ae58\"), index: 0 })) }\n\"\""
      ]
    }
  },
  "4422400": {
    "proofs": {
      "risc0": [
        "\"\""
      ]
    }
  },
  "4422500": {
    "proofs": {
      "risc0": [
        "\"\""
      ]
    }
  },
  "4422600": {
    "proofs": {
      "risc0": [
        "\"\""
      ]
    }
  },
  "4422700": {
    "proofs": {
      "risc0": [
        "\"\""
      ]
    }
  },
  "4422900": {
    "proofs": {
      "risc0": [
        "\"\""
      ]
    }
  },
  "4423000": {
    "proofs": {
      "risc0": [
        "Failed to validate block: Transaction { transaction_hash: Hash<32>(\"61b5028095fafd2a2b3af90309119201f3ae6198dd50cf6d5c9482e1d79ef42b\"), transaction_index: 0, violation: Inputs(UnknownInput(TransactionInput { transaction_id: Hash<32>(\"180fb7cfedba19697b4d164867c49ad8bf2493f6dd51d860aa03cd3e46301cb6\"), index: 0 })) }\n\"\""
      ]
    }
  },
  "4423200": {
    "proofs": {
      "risc0": [
        "Failed to validate block: Transaction { transaction_hash: Hash<32>(\"f140bb6bcc70783e5875d28e745ef303c5efadc62d4510d2c4fce54fecd118d7\"), transaction_index: 0, violation: Inputs(UnknownInput(TransactionInput { transaction_id: Hash<32>(\"ffd203301e5416ecf3fb194a5d96bbfbca494800eeae4ae0ef0ad1eb8b45604c\"), index: 0 })) }\n\"\""
      ]
    }
  },
  "4423300": {
    "proofs": {
      "risc0": [
        "Failed to validate block: Transaction { transaction_hash: Hash<32>(\"fd635be7facff18d7d0bfe953577e260e80fc582097fd3033f3e38bbd874d37d\"), transaction_index: 0, violation: Inputs(UnknownInput(TransactionInput { transaction_id: Hash<32>(\"2164285840de392aca85117e8b75eb4e90d4fe43d0cbf4a5ad6c4593ded5c2c9\"), index: 1 })) }\n\"\""
      ]
    }
  },
  "4423500": {
    "proofs": {
      "risc0": [
        "\"\""
      ]
    }
  },
  "4423800": {
    "proofs": {
      "risc0": [
        "\"\""
      ]
    }
  },
  "4423900": {
    "proofs": {
      "risc0": [
        "Failed to validate block: Transaction { transaction_hash: Hash<32>(\"efb057aeea1249005a2545a1689fcc53abc0c15e5db8c42c38d5acbb23f043cc\"), transaction_index: 0, violation: Inputs(UnknownInput(TransactionInput { transaction_id: Hash<32>(\"8348a4e65b994799d9f513f2a3628d0ebd07101581de6370cfe389b9801b9c1f\"), index: 1 })) }\n\"\""
      ]
    }
  },
  "4424000": {
    "proofs": {
      "risc0": [
        "Failed to validate block: Transaction { transaction_hash: Hash<32>(\"7a2a4426e65079c9a5b6615c090dd75a4333ad444a09b3c7fcd34605b351f896\"), transaction_index: 0, violation: Inputs(UnknownInput(TransactionInput { transaction_id: Hash<32>(\"2164285840de392aca85117e8b75eb4e90d4fe43d0cbf4a5ad6c4593ded5c2c9\"), index: 1 })) }\n\"\""
      ]
    }
  },
  "4424100": {
    "proofs": {
      "risc0": [
        "\"\""
      ]
    }
  },
  "4424200": {
    "proofs": {
      "risc0": [
        "Failed to validate block: Transaction { transaction_hash: Hash<32>(\"24d7abc311c1a24599cb0470934fd772264c36591764d89fa2e8bdeac2483bec\"), transaction_index: 0, violation: Inputs(UnknownInput(TransactionInput { transaction_id: Hash<32>(\"fffae4f0da542bbd2ee42cff7ffb9ae6766a21b64c55b70c3c745641de5c04dd\"), index: 1 })) }\n\"\""
      ]
    }
  },
  "4424300": {
    "proofs": {
      "risc0": [
        "Failed to validate block: Transaction { transaction_hash: Hash<32>(\"405b1ac11a9d788821eb7b6d103b5a31c86da67439757135361cb05c38781150\"), transaction_index: 0, violation: Inputs(UnknownInput(TransactionInput { transaction_id: Hash<32>(\"ffd203301e5416ecf3fb194a5d96bbfbca494800eeae4ae0ef0ad1eb8b45604c\"), index: 0 })) }\n\"\""
      ]
    }
  },
  "4424500": {
    "proofs": {
      "risc0": [
        "\"\""
      ]
    }
  },
  "4424600": {
    "proofs": {
      "risc0": [
        "Failed to validate block: Transaction { transaction_hash: Hash<32>(\"8dee98a84e1a09f123d9143aa2c814b4821769b87439cf9679bf904336a5db0c\"), transaction_index: 0, violation: Inputs(UnknownInput(TransactionInput { transaction_id: Hash<32>(\"4b61acedca6426ec989ef78a85ed97a8b4ffd47d9c40d4155e453d7e6b25ae58\"), index: 0 })) }\n\"\""
      ]
    }
  },
  "4424700": {
    "proofs": {
      "risc0": [
        "\"\""
      ]
    }
  },
  "4424900": {
    "proofs": {
      "risc0": [
        "Failed to validate block: Transaction { transaction_hash: Hash<32>(\"d610a2da7658027fdc843371b10a7a6d5e4244453c8537c11c7bb9e1fec27b0c\"), transaction_index: 0, violation: Inputs(UnknownInput(TransactionInput { transaction_id: Hash<32>(\"139ef4e50600cdb450e45454814008cb34f23ad55bd8d635e499571a1a2c2a6a\"), index: 1 })) }\n\"\""
      ]
    }
  },
  "4425000": {
    "proofs": {
      "risc0": [
        "Failed to validate block: Transaction { transaction_hash: Hash<32>(\"9cffe21cb3038d34729a0106576990c56784b8cf575e227801e990ff6b55f78e\"), transaction_index: 0, violation: Inputs(UnknownInput(TransactionInput { transaction_id: Hash<32>(\"9b7d0cabb05cbbe60cae6bc94d82c0784801077343842b41bb6e95b2cca4df08\"), index: 1 })) }\n\"\""
      ]
    }
  },
  "4425100": {
    "proofs": {
      "risc0": [
        "\"\""
      ]
    }
  },
  "4425300": {
    "proofs": {
      "risc0": [
        "Failed to validate block: Transaction { transaction_hash: Hash<32>(\"e6c7a27ea93d2895ab8e2a732f80c846186c127bd66740651d743720e3475198\"), transaction_index: 0, violation: Inputs(UnknownInput(TransactionInput { transaction_id: Hash<32>(\"da2608c2ed6b4b72f40a81314aa526a57762621ce3d87733d699a2dd00d9956c\"), index: 1 })) }\n\"\""
      ]
    }
  },
  "4425400": {
    "proofs": {
      "risc0": [
        "\"\""
      ]
    }
  },
  "4425500": {
    "proofs": {
      "risc0": [
        "Failed to validate block: Transaction { transaction_hash: Hash<32>(\"b86407043a2633ec816d284232dff099a3560ff871ec3cc009bdae4e2cc95c0e\"), transaction_index: 0, violation: Inputs(UnknownInput(TransactionInput { transaction_id: Hash<32>(\"3f7a5a66229806988c193e21fe43c4b4840172e9d869629b9fc521d74f34ced6\"), index: 1 })) }\n\"\""
      ]
    }
  },
  "4425700": {
    "proofs": {
      "risc0": [
        "Failed to validate block: Transaction { transaction_hash: Hash<32>(\"339064fa7ed36fcb67f3cc7ecacc1f6d67fd3113cefd3ef4b9855fd06840e3be\"), transaction_index: 0, violation: Inputs(UnknownInput(TransactionInput { transaction_id: Hash<32>(\"c45eb9f2bd7057818ef8724861c77e38367a30377186b66d5b0e81fe9549afa7\"), index: 1 })) }\n\"\""
      ]
    }
  },
  "4425800": {
    "proofs": {
      "risc0": [
        "\"\""
      ]
    }
  },
  "4426000": {
    "proofs": {
      "risc0": [
        "\"\""
      ]
    }
  },
  "4426100": {
    "proofs": {
      "risc0": [
        "\"\""
      ]
    }
  },
  "4426200": {
    "proofs": {
      "risc0": [
        "Failed to validate block: Transaction { transaction_hash: Hash<32>(\"2f216fbc70e18c1c6c1725f899087346230c9593bcc5147493d45d995c943c6b\"), transaction_index: 0, violation: Inputs(UnknownInput(TransactionInput { transaction_id: Hash<32>(\"9b7d0cabb05cbbe60cae6bc94d82c0784801077343842b41bb6e95b2cca4df08\"), index: 1 })) }\n\"\""
      ]
    }
  },
  "4426400": {
    "proofs": {
      "risc0": [
        "\"\""
      ]
    }
  },
  "4426500": {
    "proofs": {
      "risc0": [
        "\"\""
      ]
    }
  },
  "4426700": {
    "proofs": {
      "risc0": [
        "Failed to validate block: Transaction { transaction_hash: Hash<32>(\"34af6608042d96fddf810d6e16baac0a6ea17541b13ee3371e56c1503689178b\"), transaction_index: 0, violation: Inputs(UnknownInput(TransactionInput { transaction_id: Hash<32>(\"c8116c752232f272ebe79b3d1bfe96512d4b6622d2b10e6ce8dd3dd7ae1755eb\"), index: 1 })) }\n\"\""
      ]
    }
  },
  "4427000": {
    "proofs": {
      "risc0": [
        "\"\""
      ]
    }
  },
  "4427100": {
    "proofs": {
      "risc0": [
        "Failed to validate block: Transaction { transaction_hash: Hash<32>(\"e22e6c0bb73747a9faba540897d51765831e004a87c732716dc4e15b250345dc\"), transaction_index: 0, violation: Inputs(UnknownInput(TransactionInput { transaction_id: Hash<32>(\"acb67c3bd4ea8170d230a1192728bfd21666dc03c4cd806f34460e792f30a0d2\"), index: 1 })) }\n\"\""
      ]
    }
  },
  "4427200": {
    "proofs": {
      "risc0": [
        "\"\""
      ]
    }
  },
  "4427300": {
    "proofs": {
      "risc0": [
        "Failed to validate block: Transaction { transaction_hash: Hash<32>(\"9027b169ffd0fb2bad7b89a51011531e119831fef38073807dae1dc490b9eaae\"), transaction_index: 0, violation: Inputs(UnknownInput(TransactionInput { transaction_id: Hash<32>(\"d9de166c45250b031a2bb4dd8a4c01e6a83d0315c236854e87f5ee84d1eb4a18\"), index: 1 })) }\n\"\""
      ]
    }
  },
  "4427400": {
    "proofs": {
      "risc0": [
        "\"\""
      ]
    }
  },
  "4427500": {
    "proofs": {
      "risc0": [
        "\"\""
      ]
    }
  },
  "4427700": {
    "proofs": {
      "risc0": [
        "\"\""
      ]
    }
  },
  "4427800": {
    "proofs": {
      "risc0": [
        "Failed to validate block: Transaction { transaction_hash: Hash<32>(\"5cc1aa5195f228ea860fb47c7f8de1a448d6855e2847e478a72a9a8cbd47860c\"), transaction_index: 0, violation: Inputs(UnknownInput(TransactionInput { transaction_id: Hash<32>(\"ffd203301e5416ecf3fb194a5d96bbfbca494800eeae4ae0ef0ad1eb8b45604c\"), index: 0 })) }\n\"\""
      ]
    }
  },
  "4427900": {
    "proofs": {
      "risc0": [
        "Failed to validate block: Transaction { transaction_hash: Hash<32>(\"04643436d105a21cd5bd64790327cf384333a0868a875735c332e518313b5ff0\"), transaction_index: 0, violation: Inputs(UnknownInput(TransactionInput { transaction_id: Hash<32>(\"ef07212109509a9f1195f0631869694aa03b1269f0a07a745303189103176790\"), index: 1 })) }\n\"\""
      ]
    }
  },
  "4428100": {
    "proofs": {
      "risc0": [
        "\"\""
      ]
    }
  },
  "4428200": {
    "proofs": {
      "risc0": [
        "\"\""
      ]
    }
  },
  "4428300": {
    "proofs": {
      "risc0": [
        "\"\""
      ]
    }
  },
  "4428500": {
    "proofs": {
      "risc0": [
        "Failed to validate block: Transaction { transaction_hash: Hash<32>(\"d3498fae8631de61384a25719b51a26f37570fb3aaaccf8140483b0f27be95a7\"), transaction_index: 0, violation: Inputs(UnknownInput(TransactionInput { transaction_id: Hash<32>(\"ff23947a2d7d2bb2e79614f08d4aa617ca238df6989e2b17a679757a7478458c\"), index: 0 })) }\n\"\""
      ]
    }
  },
  "4428600": {
    "proofs": {
      "risc0": [
        "\"\""
      ]
    }
  }
}
