{
  "4520000": {
    "proofs": {
      "risc0": [
        "Failed to validate block: Transaction { transaction_hash: Hash<32>(\"19173368d82ee9f4df6c30b1da5e0f6a0249e84d5d2b243383561a39fc5b177d\"), transaction_index: 0, violation: Inputs(UnknownInput(TransactionInput { transaction_id: Hash<32>(\"2164285840de392aca85117e8b75eb4e90d4fe43d0cbf4a5ad6c4593ded5c2c9\"), index: 1 })) }\n\"\""
      ]
    }
  },
  "4520100": {
    "proofs": {
      "risc0": [
        "\"\""
      ]
    }
  },
  "4520200": {
    "proofs": {
      "risc0": [
        "\"\""
      ]
    }
  },
  "4520300": {
    "proofs": {
      "risc0": [
        "Failed to validate block: Transaction { transaction_hash: Hash<32>(\"025f9c0b3a9fbf99fc29f1cb332ff749f7a604385f80d461324f1b6557e8e651\"), transaction_index: 0, violation: Inputs(UnknownInput(TransactionInput { transaction_id: Hash<32>(\"7842bf8914485e44b460a8a86b0042bd103644d58af5d20f36fd9c97c7c6d5a4\"), index: 0 })) }\n\"\""
      ]
    }
  },
  "4520400": {
    "proofs": {
      "risc0": [
        "Failed to validate block: Transaction { transaction_hash: Hash<32>(\"e9c6c3e1f9577ccadb450480dc8ebddcf1dc3df1d7e721aacf72c420f3fd78cc\"), transaction_index: 0, violation: Inputs(UnknownInput(TransactionInput { transaction_id: Hash<32>(\"267afc49bb8ad6165baf54eafcf7c147f021b75adc71531cb7f8a6f13fe06d76\"), index: 1 })) }\n\"\""
      ]
    }
  },
  "4520600": {
    "proofs": {
      "risc0": [
        "Failed to validate block: Transaction { transaction_hash: Hash<32>(\"0aaaefca2a3b9ca11ae9363685b2b4a05a35b3a980069884a9c1873e66a934d7\"), transaction_index: 0, violation: Inputs(UnknownInput(TransactionInput { transaction_id: Hash<32>(\"5ebe588d33e3e418514360379c1d7143f1a8bfcf28f17a824c226a2ede508618\"), index: 0 })) }\n\"\""
      ]
    }
  },
  "4520700": {
    "proofs": {
      "risc0": [
        "Failed to validate block: Transaction { transaction_hash: Hash<32>(\"2695ebdaf5943cc0fc93469ba9a92b256b544209e471928d763d6a50d5e43500\"), transaction_index: 0, violation: Inputs(UnknownInput(TransactionInput { transaction_id: Hash<32>(\"b15fb0eac24bfea1984dcff2c8a3817b8901c3c939b1055b54c8772f89b9ca2c\"), index: 1 })) }\n\"\""
      ]
    }
  },
  "4520900": {
    "proofs": {
      "risc0": [
        "Failed to validate block: Transaction { transaction_hash: Hash<32>(\"7269de0d03abe3f99fb721daf874b26dbf33f5948794be1039a496000b8b4678\"), transaction_index: 0, violation: Inputs(UnknownInput(TransactionInput { transaction_id: Hash<32>(\"dd53461fda51a8170e3b510dfd3f19b71ea5ad88015ad74ff606aa314bad80eb\"), index: 0 })) }\n\"\""
      ]
    }
  },
  "4521000": {
    "proofs": {
      "risc0": [
        "Failed to validate block: Transaction { transaction_hash: Hash<32>(\"8e5d0540dff925139b5eb24ad2698722d5725aa96da0ab691f88305d3459e02e\"), transaction_index: 0, violation: Inputs(UnknownInput(TransactionInput { transaction_id: Hash<32>(\"d062bb37553709a4cb7b452130040eb99220c1b5cf17253d44701d3d4ff1bf81\"), index: 4 })) }\n\"\""
      ]
    }
  },
  "4521300": {
    "proofs": {
      "risc0": [
        "\"\""
      ]
    }
  },
  "4521400": {
    "proofs": {
      "risc0": [
        "\"\""
      ]
    }
  },
  "4521600": {
    "proofs": {
      "risc0": [
        "Failed to validate block: Transaction { transaction_hash: Hash<32>(\"b69e982e8006ef2877f8407de7c27993fda62eefab803de0ed1f72556a311766\"), transaction_index: 0, violation: Inputs(UnknownInput(TransactionInput { transaction_id: Hash<32>(\"b31179a89f31d9b08bc0f075a4661c72a31c2270eb27ce42f9d4170180118def\"), index: 0 })) }\n\"\""
      ]
    }
  },
  "4521700": {
    "proofs": {
      "risc0": [
        "Failed to validate block: Transaction { transaction_hash: Hash<32>(\"2fa7fb9ce5a10f02ecd1041c9d74dc7350f0775ce8d1e58594c2404a95bf157a\"), transaction_index: 0, violation: Inputs(UnknownInput(TransactionInput { transaction_id: Hash<32>(\"9b7d0cabb05cbbe60cae6bc94d82c0784801077343842b41bb6e95b2cca4df08\"), index: 1 })) }\n\"\""
      ]
    }
  },
  "4521800": {
    "proofs": {
      "risc0": [
        "\"\""
      ]
    }
  },
  "4522000": {
    "proofs": {
      "risc0": [
        "Failed to validate block: Transaction { transaction_hash: Hash<32>(\"44d7b173e9cffffc77b8c42ff7021382a55887221eaff2ebda07d14d7e4820d1\"), transaction_index: 0, violation: Inputs(UnknownInput(TransactionInput { transaction_id: Hash<32>(\"384c0e6312416e2889b4ac88777ccf62376af8e808c817052f4627242ea56e2f\"), index: 2 })) }\n\"\""
      ]
    }
  },
  "4522100": {
    "proofs": {
      "risc0": [
        "\"\""
      ]
    }
  },
  "4522200": {
    "proofs": {
      "risc0": [
        "\"\""
      ]
    }
  },
  "4522300": {
    "proofs": {
      "risc0": [
        "Failed to validate block: Transaction { transaction_hash: Hash<32>(\"053e351b6b06e8e8ddbe515c17ddc8d6a7c96812c14baa791f1e61008ad51540\"), transaction_index: 0, violation: Inputs(UnknownInput(TransactionInput { transaction_id: Hash<32>(\"ed00faf0b8d73e959e727419bf78ce4c67966c2dbb385455a8c036137a418255\"), index: 2 })) }\n\"\""
      ]
    }
  },
  "4522400": {
    "proofs": {
      "risc0": [
        "\"\""
      ]
    }
  },
  "4522600": {
    "proofs": {
      "risc0": [
        "Failed to validate block: Transaction { transaction_hash: Hash<32>(\"32d05dbf28f2fe8739162e270eca056542e1d2c7149a7b6dff8d1fb87a7eb879\"), transaction_index: 0, violation: Inputs(UnknownInput(TransactionInput { transaction_id: Hash<32>(\"44ad37f8377ceb356cdedbe68143330be34fc5761e94ef9e65c12d988fc99c68\"), index: 1 })) }\n\"\""
      ]
    }
  },
  "4522700": {
    "proofs": {
      "risc0": [
        "Failed to validate block: Transaction { transaction_hash: Hash<32>(\"915b41bc21d911de13c5bfaba42ad4a9d8d29bc4b8b88740629a0d8dc54aae89\"), transaction_index: 0, violation: Inputs(UnknownInput(TransactionInput { transaction_id: Hash<32>(\"4818de1aba84c5b73ccdbe6a738d4d08b19615779beec323f2c7a29adf13bf3c\"), index: 0 })) }\n\"\""
      ]
    }
  },
  "4522800": {
    "proofs": {
      "risc0": [
        "\"\""
      ]
    }
  },
  "4523100": {
    "proofs": {
      "risc0": [
        "\"\""
      ]
    }
  },
  "4523200": {
    "proofs": {
      "risc0": [
        "\"\""
      ]
    }
  },
  "4523300": {
    "proofs": {
      "risc0": [
        "\"\""
      ]
    }
  },
  "4523400": {
    "proofs": {
      "risc0": [
        "Failed to validate block: Transaction { transaction_hash: Hash<32>(\"f350aa3c764969f73729833cc0c562dddc38d3d87e0bb57b213dbdd109780248\"), transaction_index: 0, violation: Inputs(UnknownInput(TransactionInput { transaction_id: Hash<32>(\"30d111d43e228812ac6eaec4d19a6fbb73c16126a536cafc20d662e7f93c02d9\"), index: 0 })) }\n\"\""
      ]
    }
  },
  "4523600": {
    "proofs": {
      "risc0": [
        "\"\""
      ]
    }
  },
  "4523700": {
    "proofs": {
      "risc0": [
        "\"\""
      ]
    }
  }
}
